mikrot8over/__init__.py
mikrot8over/mikrot8over.py
mikrot8over-1.1.dist-info/LICENSE
mikrot8over-1.1.dist-info/METADATA
mikrot8over-1.1.dist-info/WHEEL
mikrot8over-1.1.dist-info/entry_points.txt
mikrot8over-1.1.dist-info/top_level.txt
mikrot8over-1.1.dist-info/RECORD
